sbmltoodepy/__init__.py
sbmltoodepy/dataclasses.py
sbmltoodepy/modelclasses.py
sbmltoodepy/modulegeneration.py
sbmltoodepy/parse.py
sbmltoodepy/utilities.py
sbmltoodepy/sbml_files/Borisov2009_insulin_EGF.xml
sbmltoodepy/sbml_files/Guyton1972_Angiotensin.xml
sbmltoodepy/sbml_files/Kerkhoven2013_Glycolysis_in_T_brucei.xml
sbmltoodepy/sbml_files/Smallbone2013_Colon_Crypt_cycle.xml
sbmltoodepy/sbml_files/Waugh2006_Diabetic_Wound_Healing_TGF_B_Dynamics.xml
sbmltoodepy/sbml_files/Zi2011_TGF_beta_Pathway.xml
sbmltopyode/ModelDataClasses.py
sbmltopyode/ParseAndGenerate.py
sbmltopyode/SBMLModelClasses.py
sbmltopyode/SBMLparser.py
sbmltopyode/__init__.py
sbmltopyode/python3ClassGenerator.py
sbmltoodepy-1.0.3.post1.dist-info/LICENSE
sbmltoodepy-1.0.3.post1.dist-info/METADATA
sbmltoodepy-1.0.3.post1.dist-info/WHEEL
sbmltoodepy-1.0.3.post1.dist-info/top_level.txt
sbmltoodepy-1.0.3.post1.dist-info/RECORD
