Metadata-Version: 2.1
Name: sbmltoodepy
Version: 1.0.3.post1
Summary: A package that creates a python implementation of an SBML model.
Home-page: https://github.com/SMRuggiero/sbmltoodepy
Author: Steve M Ruggiero, Ashlee N Ford Versypt
Author-email: SteveMRuggiero@gmail.com
License: UNKNOWN
Platform: UNKNOWN
Classifier: Programming Language :: Python :: 3
Classifier: License :: OSI Approved :: BSD License
Classifier: Operating System :: OS Independent
Requires-Dist: python-libsbml
Requires-Dist: numpy
Requires-Dist: scipy
